bdshare/__init__.py
bdshare/_version.py
bdshare/stock/__init__.py
bdshare/stock/market.py
bdshare/stock/news.py
bdshare/stock/trading.py
bdshare/util/__init__.py
bdshare/util/cons.py
bdshare/util/session.py
bdshare/util/store.py
bdshare/util/tickers.py
bdshare/util/upass.py
bdshare/util/vars.py
bdshare-1.1.4.dist-info/licenses/LICENSE
tests/__init__.py
tests/test_market.py
tests/test_news.py
tests/test_random.py
tests/test_trading.py
bdshare-1.1.4.dist-info/METADATA
bdshare-1.1.4.dist-info/WHEEL
bdshare-1.1.4.dist-info/top_level.txt
bdshare-1.1.4.dist-info/RECORD
