Metadata-Version: 2.4
Name: bdshare
Version: 1.1.4
Summary: A utility for crawling historical and Real-time Quotes of DSE(Dhaka Stock Exchange)
Author: Raisul Islam
Author-email: raisul.me@gmail.com
License: MIT
Keywords: Crawling,DSE,Financial Data
Classifier: Programming Language :: Python :: 3
Requires-Python: >=3.9
License-File: LICENSE
Requires-Dist: requests
Requires-Dist: beautifulsoup4
Requires-Dist: html5lib
Requires-Dist: pandas
Requires-Dist: lxml
Dynamic: license-file
